{
  "schema": "ddp-training-v1",
  "torch_version": "2.9.0+cu128",
  "nccl_version": [
    2,
    27,
    5
  ],
  "gpu": "NVIDIA H800",
  "world_size": 4,
  "config": {
    "bs_per_gpu": 10,
    "patch": 170,
    "out_channel": 96,
    "depth": 4,
    "n_routed": 12,
    "top_k": 2,
    "combine": "grouped",
    "cap_factor": 1.25,
    "attn": "sdpa",
    "compile": true,
    "compile_mode": "default",
    "bucket_cap_mb": 25.0,
    "gradient_as_bucket_view": true,
    "find_unused_parameters": true,
    "static_graph": false,
    "fused_adam": true,
    "comm_mode": "default",
    "checkpoint": "/ytech_m2v4_hdd/lizhongyin/code/Graduation-Paper/models/Ours_v3_frozen/model_26.pth"
  },
  "measurement": {
    "warmup_steps": 10,
    "steps": 20,
    "critical_step_ms": [
      425.1748670358211,
      425.028256024234,
      424.9826699960977,
      424.58658100804314,
      425.86619296343997,
      424.6859150007367,
      425.3916179877706,
      426.1257089674473,
      424.2737269960344,
      424.2458869703114,
      424.31519395904616,
      425.26083800476044,
      424.68328500399366,
      425.2702860394493,
      424.7872050036676,
      425.24090001825243,
      425.14223902253434,
      425.03221798688173,
      425.0203400151804,
      424.6890570502728
    ],
    "mean_step_ms": 424.99014925269876,
    "std_step_ms": 0.48657655019584345,
    "p50_step_ms": 425.0242980197072,
    "p95_step_ms": 425.87916876364034,
    "global_samples_per_second": 94.11982858975877,
    "rank_time_cv_mean": 0.0003372031476632344,
    "rank_gap_ms_mean": 0.20970117693650536,
    "rank_mean_step_ms": 424.78044807576225,
    "peak_memory_gb": 69.520285184,
    "warmup_seconds_including_compile": 24.159652551985346,
    "last_loss": 2.2115546022705836
  },
  "ddp_logging": {
    "backend_name": "nccl",
    "bucket_sizes": "16434656",
    "cuda_visible_devices": "0,1,2,3",
    "device_ids": "0",
    "dtypes": "float",
    "master_addr": "aiplatform-wlf3-ge98-285.idchb2az3.hb2.kwaidc.com",
    "master_port": "41757",
    "module_name": "OptimizedModule",
    "nccl_async_error_handling": "1",
    "nccl_blocking_wait": "N/A",
    "nccl_debug": "N/A",
    "nccl_ib_timeout": "N/A",
    "nccl_nthreads": "N/A",
    "nccl_socket_ifname": "N/A",
    "prev_iteration_grad_ready_order_indices": "26, 27, 231, 235, 251, 236, 253, 249, 278, 274, 270, 266, 262, 258, 254, 250, 246, 242, 238, 234, 277, 273, 269, 265, 261, 232, 245, 241, 237, 233, 276, 272, 268, 264, 260, 256, 252, 248, 244, 257, 247, 275, 271, 267, 263, 259, 240, 239, 243, 255, 227, 228, 279, 230, 229, 218, 219, 223, 226, 225, 220, 221, 224, 222, 169, 173, 189, 174, 191, 187, 216, 212, 208, 204, 200, 196, 192, 188, 184, 180, 176, 172, 215, 211, 207, 203, 199, 170, 183, 179, 175, 171, 214, 210, 206, 202, 198, 194, 190, 186, 182, 195, 185, 213, 209, 205, 201, 197, 178, 177, 181, 193, 165, 166, 217, 168, 167, 156, 157, 161, 164, 163, 158, 159, 162, 160, 107, 111, 127, 112, 129, 125, 154, 150, 146, 142, 138, 134, 130, 126, 122, 118, 114, 110, 153, 149, 145, 141, 137, 108, 121, 117, 113, 109, 152, 148, 144, 140, 136, 132, 128, 124, 120, 133, 123, 151, 147, 143, 139, 135, 116, 115, 119, 131, 103, 104, 155, 106, 105, 94, 95, 99, 102, 101, 96, 97, 100, 98, 45, 49, 65, 50, 67, 63, 92, 88, 84, 80, 76, 72, 68, 64, 60, 56, 52, 48, 91, 87, 83, 79, 75, 46, 59, 55, 51, 47, 90, 86, 82, 78, 74, 70, 66, 62, 58, 71, 61, 89, 85, 81, 77, 73, 54, 53, 57, 69, 41, 42, 93, 43, 44, 32, 36, 34, 40, 39, 38, 33, 35, 37, 13, 16, 22, 24, 25, 23, 21, 20, 19, 18, 14, 15, 17, 29, 28, 0, 2, 5, 12, 11, 10, 8, 7, 4, 6, 9, 1, 3",
    "torch_distributed_debug": "N/A",
    "avg_backward_comm_time": 1182586618,
    "avg_backward_compute_comm_overlap_time": 57895,
    "avg_backward_compute_time": 316176001,
    "avg_forward_compute_time": 912775256,
    "backward_comm_time": 979808,
    "backward_comm_time_end": 1784442696978011966,
    "backward_comm_time_start": 1784442696886464769,
    "backward_compute_comm_overlap_time": 7744,
    "backward_compute_time": 275443136,
    "backward_compute_time_end": 1784442696886736150,
    "backward_compute_time_start": 1784442696699836598,
    "broadcast_buffers": 1,
    "bucket_cap_bytes": 26214400,
    "find_unused_parameters": 1,
    "forward_compute_time": 145894592,
    "forward_compute_time_start": 1784442696555701185,
    "gradient_as_bucket_view": 1,
    "has_rebuilt_buckets": 0,
    "has_sync_bn": 0,
    "is_multi_device_module": 0,
    "iteration": 10,
    "num_buckets_reduced": 1,
    "num_parameter_tensors": 280,
    "output_device": 0,
    "rank": 0,
    "total_parameter_size_bytes": 16434656,
    "unused_parameter_size": 768,
    "world_size": 4
  },
  "routing_by_rank": [
    {
      "dispatches": 6936000,
      "dropped": 42290,
      "load_cv_mean": 0.15046823157368477,
      "max_over_mean_mean": 1.2704480968858132,
      "drop_pct": 0.609717416378316
    },
    {
      "dispatches": 6936000,
      "dropped": 44789,
      "load_cv_mean": 0.1522686218783594,
      "max_over_mean_mean": 1.2746695501730105,
      "drop_pct": 0.6457468281430219
    },
    {
      "dispatches": 6936000,
      "dropped": 50780,
      "load_cv_mean": 0.15377166788745078,
      "max_over_mean_mean": 1.282634948096886,
      "drop_pct": 0.7321222606689735
    },
    {
      "dispatches": 6936000,
      "dropped": 40193,
      "load_cv_mean": 0.1484041833493541,
      "max_over_mean_mean": 1.2672750865051905,
      "drop_pct": 0.5794838523644752
    }
  ]
}
